{"format_2.md":"6f2f7416","format_1.md":"e96cfc4d","index.md":"0d730ede","utils_npm.md":"17eb337b","issues_uni-app.md":"5a202fe0","issues_vue-component.md":"bced6481","issues_vue3.md":"a819964f","os_linux.md":"e3f39d66","os_mac.md":"b9f7c88d","format_3.md":"79278c1c","others_component-library.md":"b9386dd7","others_node-library.md":"b00ea22c","others_sites_blogs.md":"db89dd12","others_uni-app.md":"707ae9ab","issues_https.md":"3ea9ff66","utils_charles.md":"942b8888","utils_git.md":"342bb88e","issues_github.md":"b41506ae","utils_pnpm.md":"baa5d2b6","issues_gulp.md":"9a23bd42","utils_vscode.md":"6321279e","utils_nginx.md":"f9e00bd8","issues_nuxt3.md":"e692d634","issues_shelljs.md":"14fa5048","issues_pinia.md":"d4753326","issues_font.md":"79876a93","issues_npm.md":"6d9365e8"}
